setup.py
permkeep/__init__.py
permkeep.egg-info/PKG-INFO
permkeep.egg-info/SOURCES.txt
permkeep.egg-info/dependency_links.txt
permkeep.egg-info/top_level.txt
permkeep/management/__init__.py
permkeep/management/commands/__init__.py
permkeep/management/commands/setperms.py