Metadata-Version: 1.0
Name: permkeep
Version: 12.05.1
Summary: Easy way to keep group permissions in sync between Development and Production environments.
Home-page: https://github.com/pizzapanther/Django-Permissions-Keeper
Author: Paul Bailey
Author-email: paul.m.bailey@gmail.com
License: BSD
Platform: UNKNOWN
